[
    {
        "id": "dc6c253dbed13f79",
        "type": "inject",
        "z": "ea4982f4f2256a14",
        "name": "",
        "props": [
            {
                "p": "payload"
            },
            {
                "p": "topic",
                "vt": "str"
            }
        ],
        "repeat": "1",
        "crontab": "",
        "once": false,
        "onceDelay": 0.1,
        "topic": "",
        "payload": "",
        "payloadType": "date",
        "x": 130,
        "y": 300,
        "wires": [
            [
                "01a77fecbe173bd3",
                "7a8eb37da4de5f15",
                "910107898b080d9e"
            ]
        ]
    }
]